{
    "word_coordinate": [
        199.537659,
        -682.93866,
        470.711365,
        89.999992,
        0.002673,
        0.002155
    ],
    "joint_coordinate": [
        -70.465935,
        -33.781357,
        -23.659866,
        22.825886,
        59.52277,
        77.946968
    ],
    "a_min": -100.0,
    "a_max": 100.0,
    "b_min": -100.0,
    "b_max": 100.0,
    "a_step": 50.0,
    "b_step": 50.0,
    "mode": "xOz",
    "f_min": "10000000000",
    "f_max": "18000000000",
    "f_step": "101",
    "f_times": "1",
    "save_folder": "./Data",
    "save_file": "system_test2.csv"
}